ficus/__init__.py
ficus/grpc_pipelines/__init__.py
ficus/grpc_pipelines/activities_parts.py
ficus/grpc_pipelines/annotations.py
ficus/grpc_pipelines/cases_parts.py
ficus/grpc_pipelines/clustering.py
ficus/grpc_pipelines/constants.py
ficus/grpc_pipelines/context_values.py
ficus/grpc_pipelines/data_models.py
ficus/grpc_pipelines/discovery_parts.py
ficus/grpc_pipelines/drawing_parts.py
ficus/grpc_pipelines/filtering_parts.py
ficus/grpc_pipelines/multithreading.py
ficus/grpc_pipelines/mutation_parts.py
ficus/grpc_pipelines/patterns_parts.py
ficus/grpc_pipelines/util_parts.py
ficus/grpc_pipelines/xes_parts.py
ficus/grpc_pipelines/entry_points/__init__.py
ficus/grpc_pipelines/entry_points/default_pipeline.py
ficus/grpc_pipelines/entry_points/kafka.py
ficus/grpc_pipelines/entry_points/sreaming_configuration.py
ficus/grpc_pipelines/entry_points/util.py
ficus/grpc_pipelines/models/__init__.py
ficus/grpc_pipelines/models/backend_service_pb2.py
ficus/grpc_pipelines/models/backend_service_pb2.pyi
ficus/grpc_pipelines/models/backend_service_pb2_grpc.py
ficus/grpc_pipelines/models/context_values_service_pb2.py
ficus/grpc_pipelines/models/context_values_service_pb2.pyi
ficus/grpc_pipelines/models/context_values_service_pb2_grpc.py
ficus/grpc_pipelines/models/front_contract_pb2.py
ficus/grpc_pipelines/models/front_contract_pb2.pyi
ficus/grpc_pipelines/models/front_contract_pb2_grpc.py
ficus/grpc_pipelines/models/kafka_service_pb2.py
ficus/grpc_pipelines/models/kafka_service_pb2.pyi
ficus/grpc_pipelines/models/kafka_service_pb2_grpc.py
ficus/grpc_pipelines/models/pipelines_and_context_pb2.py
ficus/grpc_pipelines/models/pipelines_and_context_pb2.pyi
ficus/grpc_pipelines/models/pipelines_and_context_pb2_grpc.py
ficus/grpc_pipelines/models/pm_models_pb2.py
ficus/grpc_pipelines/models/pm_models_pb2.pyi
ficus/grpc_pipelines/models/pm_models_pb2_grpc.py
ficus/grpc_pipelines/models/util_pb2.py
ficus/grpc_pipelines/models/util_pb2.pyi
ficus/grpc_pipelines/models/util_pb2_grpc.py
ficus_pm-1.0.6.dist-info/METADATA
ficus_pm-1.0.6.dist-info/WHEEL
ficus_pm-1.0.6.dist-info/top_level.txt
ficus_pm-1.0.6.dist-info/RECORD
