Metadata-Version: 2.4
Name: ficus-pm
Version: 1.0.6
Summary: The modern Process Mining toolkit
Author: Aero
Author-email: aerooneq@yandex.ru
License: private
Requires-Dist: pm4py==2.7.7
Requires-Dist: matplotlib==3.8.0
Requires-Dist: matplotlib-inline==0.1.6
Requires-Dist: graphviz~=0.20.1
Requires-Dist: intervaltree~=3.1.0
Requires-Dist: ipython==8.16.1
Requires-Dist: numpy~=1.26.0
Requires-Dist: pandas==2.1.1
Requires-Dist: setuptools==68.2.2
Requires-Dist: python-dateutil~=2.8.2
Requires-Dist: ipycanvas~=0.13.1
Requires-Dist: pytest~=7.4.2
Requires-Dist: grpcio==1.59.0
Requires-Dist: grpcio-tools==1.59.0
Requires-Dist: suffix-tree==0.1.2
Requires-Dist: scikit-learn~=1.3.2
Requires-Dist: attrs~=23.1.0
Requires-Dist: docker~=7.1.0
Dynamic: author
Dynamic: author-email
Dynamic: description
Dynamic: description-content-type
Dynamic: license
Dynamic: requires-dist
Dynamic: summary
